aiocache/__init__.py
aiocache/base.py
aiocache/decorators.py
aiocache/exceptions.py
aiocache/factory.py
aiocache/lock.py
aiocache/plugins.py
aiocache/backends/__init__.py
aiocache/backends/memcached.py
aiocache/backends/memory.py
aiocache/backends/redis.py
aiocache/serializers/__init__.py
aiocache/serializers/serializers.py
aiocache-0.12.3.dist-info/LICENSE
aiocache-0.12.3.dist-info/METADATA
aiocache-0.12.3.dist-info/WHEEL
aiocache-0.12.3.dist-info/top_level.txt
aiocache-0.12.3.dist-info/RECORD
