Metadata-Version: 2.1
Name: aiocache
Version: 0.12.3
Summary: multi backend asyncio cache
Home-page: https://github.com/aio-libs/aiocache
Author: Manuel Miranda
Author-email: manu.mirandad@gmail.com
Classifier: Programming Language :: Python
Classifier: Programming Language :: Python :: 3.7
Classifier: Programming Language :: Python :: 3.8
Classifier: Programming Language :: Python :: 3.9
Classifier: Programming Language :: Python :: 3.10
Classifier: Programming Language :: Python :: 3.11
Classifier: Framework :: AsyncIO
License-File: LICENSE
Provides-Extra: redis
Requires-Dist: redis>=4.2.0; extra == "redis"
Provides-Extra: memcached
Requires-Dist: aiomcache>=0.5.2; extra == "memcached"
Provides-Extra: msgpack
Requires-Dist: msgpack>=0.5.5; extra == "msgpack"
